[{"nn_end":null,"nn_start":null,"start":1.0,"className":"blue","end":150.0,"id":"j8B4Rw","content":"fruehkaiserzeitlich"},{"nn_end":null,"nn_start":null,"start":50.0,"className":"blue","end":100.0,"id":"D08W63","content":"2ndHalfFirstCentury"},{"nn_end":null,"nn_start":null,"start":69.0,"className":"blue","end":69.0,"id":"D3ymk1","type":"point","content":"Usurpator"},{"nn_end":null,"nn_start":null,"start":69.0,"className":"blue","end":69.0,"id":"ka7M2y","type":"point","content":"Galba"},{"nn_end":null,"nn_start":null,"start":69.0,"className":"blue","end":69.0,"id":"NLOA8e","type":"point","content":"Otho"},{"nn_end":null,"nn_start":null,"start":69.0,"className":"blue","end":79.0,"id":"lxDzqd","content":"Vespasian"},{"nn_end":null,"nn_start":null,"start":79.0,"className":"blue","end":81.0,"id":"y1D3WN","content":"Titus"},{"nn_end":null,"nn_start":null,"start":81.0,"className":"blue","end":96.0,"id":"V9Epa6","content":"Domitian"},{"nn_end":null,"nn_start":null,"start":96.0,"className":"blue","end":98.0,"id":"Qb1g7K","content":"Nerva"},{"nn_end":null,"nn_start":null,"start":98.0,"className":"blue","end":117.0,"id":"g7Vdrx","content":"Trajan"},{"nn_end":null,"nn_start":null,"start":69.0,"className":"blue","end":69.0,"id":"R6EL45","type":"point","content":"Vitellius"},{"nn_end":"Domitian","nn_start":"Domitian","start":81.0,"className":"orange","end":96.0,"id":"KwyAGQ","content":"DomitianConsulate2-->Domitian,Domitian"}]